undiscord.py
undiscord-1.53.data/scripts/undiscord
undiscord-1.53.dist-info/LICENSE
undiscord-1.53.dist-info/METADATA
undiscord-1.53.dist-info/WHEEL
undiscord-1.53.dist-info/top_level.txt
undiscord-1.53.dist-info/RECORD
