Metadata-Version: 2.1
Name: undiscord
Version: 1.53
Summary: Bulk wipe messages in a Discord server or DM using a Python interpreter on Android or PC.
Home-page: https://github.com/HardcodedCat/undiscord-python
Author: HardcodedCat
License: MIT
Keywords: setuptools,undiscord,discord,wipe,delete,erase,messages,selfbot,userscript
Platform: any
Classifier: Development Status :: 4 - Beta
Classifier: Environment :: Console
Classifier: Intended Audience :: End Users/Desktop
Classifier: License :: OSI Approved :: MIT License
Classifier: Natural Language :: English
Classifier: Natural Language :: Portuguese
Classifier: Natural Language :: Portuguese (Brazilian)
Classifier: Operating System :: Android
Classifier: Operating System :: MacOS
Classifier: Operating System :: Microsoft :: Windows
Classifier: Operating System :: OS Independent
Classifier: Operating System :: POSIX
Classifier: Operating System :: Unix
Classifier: Programming Language :: Python
Classifier: Programming Language :: Python :: 3
Classifier: Programming Language :: Python :: 3 :: Only
Classifier: Programming Language :: Python :: 3.7
Classifier: Programming Language :: Python :: 3.8
Classifier: Programming Language :: Python :: 3.9
Classifier: Programming Language :: Python :: 3.10
Classifier: Topic :: Communications :: Chat
Classifier: Topic :: Communications :: Chat :: Internet Relay Chat
Classifier: Topic :: Internet
Classifier: Topic :: Utilities
Classifier: Typing :: Typed
Requires-Python: >=3.7
License-File: LICENSE
Requires-Dist: furl
Requires-Dist: pwinput
Requires-Dist: icmplib
Requires-Dist: alive-progress
